{
  "Messages": {
    "18": {
      "MessageId": 18,
      "MergeRequestId": 122925,
      "Title": "Draft: Initial commit",
      "Link": "https://gitlab.dats.tech/datsteam/hebrew/android/-/merge_requests/18",
      "Status": "opened",
      "AuthorUserName": "g.ter-grigoryants",
      "HasComments": false
    },
    "19": {
      "MessageId": 19,
      "MergeRequestId": 582638,
      "Title": "",
      "Link": "https://gitlab.dats.tech/datsteam/hebrew/android/-/merge_requests/18#note_582638",
      "Status": "",
      "AuthorUserName": "g.ter-grigoryants",
      "HasComments": true
    },
    "20": {
      "MessageId": 20,
      "MergeRequestId": 582639,
      "Title": "",
      "Link": "https://gitlab.dats.tech/datsteam/hebrew/android/-/merge_requests/18#note_582639",
      "Status": "",
      "AuthorUserName": "g.ter-grigoryants",
      "HasComments": true
    }
  }
}